cdrouter/__init__.py
cdrouter/alerts.py
cdrouter/annotations.py
cdrouter/attachments.py
cdrouter/captures.py
cdrouter/cdr_datetime.py
cdrouter/cdr_error.py
cdrouter/cdrouter.py
cdrouter/configs.py
cdrouter/devices.py
cdrouter/exports.py
cdrouter/filters.py
cdrouter/highlights.py
cdrouter/history.py
cdrouter/imports.py
cdrouter/jobs.py
cdrouter/metrics.py
cdrouter/packages.py
cdrouter/results.py
cdrouter/system.py
cdrouter/tags.py
cdrouter/testresults.py
cdrouter/testsuites.py
cdrouter/users.py
cdrouter-0.9.7.dist-info/LICENSE.txt
cdrouter-0.9.7.dist-info/METADATA
cdrouter-0.9.7.dist-info/WHEEL
cdrouter-0.9.7.dist-info/top_level.txt
cdrouter-0.9.7.dist-info/RECORD
